{
  "1": { "field": "value", "name": "year" },
  "2": { "field": "value", "name": "fuel"},
  "3": { "field": "value", "name": "motorType"},
  "4": { "field": "value", "name": "transmission"},
  "5": { "field": "value", "name": "bodyStyle"},
  "7": { "field": "value", "name": "cylinders"},
  "8": { "field": "value", "name": "damageType"},
  "9": { "field": "value", "name": "primaryDamage"},
  "10": { "field": "value", "name": "secondaryDamage"},
  "11": { "field": "value", "name": "color"},
  "13": { "field": "value", "name": "driveTrain"},
  "18": { "field": "value", "name": "keys"},
  "19": { "field": "value", "name": "airbags"},
  "20": { "field": "value", "name": "airbags2"},
  "24": { "field": "value", "name": "odometer"},
  "25": { "field": "value", "name": "odometerActuality"},
  "28": { "field": "value", "name": "keys2"},
  "30": { "field": "value", "name": "complectation"},
  "33": { "field": "value", "name": "motorVolume"},
  "34": { "field": "value", "name": "manufacturer"},
  "35": { "field": "value", "name": "model"},
  "36": { "field": "value", "name": "lotType"},
  "40": { "field": "value", "name": "buyerLimitations"},
  "41": { "field": "value", "name": "certificateTitle"},
  "42": { "field": "value", "name": "countryLocation"},
  "43": { "field": "value", "name": "countryState"},
  "44": { "field": "value", "name": "locationAria"},
  "49": { "field": "note", "name": "locationName"},
  "51": { "field": "value", "name": "abilityToDrive"},
  "54": { "field": "value", "name": "odometerType"},
  "57": { "field": "value", "name": "saleType"}
}